CPU/logic.vhdl
--basic logic components of the ALU
library ieee;
use ieee.std_logic_1164.all;

entity INV is
  port (A: in std_logic;
  F: out std_logic);
end INV;

architecture INV_beh of INV is
begin
    F <= not A;
end architecture;

library ieee;
use ieee.std_logic_1164.all;

entity dual_AND is
  port (A: in std_logic;
  B: in std_logic;
  F: out std_logic);
end dual_AND;

architecture dual_AND_beh of dual_AND is
begin
    F <= A and B;
end architecture;

library ieee;
use ieee.std_logic_1164.all;

entity triple_AND is
  port (A: in std_logic;
  B: in std_logic;
  C: in std_logic;
  F: out std_logic);
end triple_AND;

architecture triple_AND_beh of triple_AND is
begin
    F <= A and B and C;
end architecture;

library ieee;
use ieee.std_logic_1164.all;

entity quad_AND is
  port (A: in std_logic;
  B: in std_logic;
  C: in std_logic;
  D: in std_logic;
  F: out std_logic);
end quad_AND;

architecture quad_AND_beh of quad_AND is
begin
    F <= A and B and C and D;
end architecture;

library ieee;
use ieee.std_logic_1164.all;

entity pent_AND is
  port (A: in std_logic;
  B: in std_logic;
  C: in std_logic;
  D: in std_logic;
  E: in std_logic;
  F: out std_logic);
end pent_AND;

architecture pent_AND_beh of pent_AND is
begin
    F <= A and B and C and D and E;
end architecture;

library ieee;
use ieee.std_logic_1164.all;

entity dual_XOR is
  port(A: in std_logic;
  B: in std_logic;
  F: out std_logic);
end dual_XOR;

architecture dual_XOR_beh of dual_XOR is
begin
  F <= A xor B;
end architecture;

library ieee;
use ieee.std_logic_1164.all;

entity dual_NOR is
  port(A: in std_logic;
  B: in std_logic;
  F: out std_logic);
end dual_NOR;

architecture dual_NOR_beh of dual_NOR is
begin
  F <= A nor B;
end architecture;

library ieee;
use ieee.std_logic_1164.all;

entity triple_NOR is
  port(A: in std_logic;
  B: in std_logic;
  C: in std_logic;
  F: out std_logic);
end triple_NOR;

architecture triple_NOR_beh of triple_NOR is
begin
  F <= ((not A) and (not B) and (not C));
end architecture;

library ieee;
use ieee.std_logic_1164.all;

entity quad_NOR is
  port(A: in std_logic;
  B: in std_logic;
  C: in std_logic;
  D: in std_logic;
  F: out std_logic);
end quad_NOR;

architecture quad_NOR_beh of quad_NOR is
begin
  F <= ((not A) and (not B) and (not C) and (not D));
end architecture;

library ieee;
use ieee.std_logic_1164.all;

entity BUF is
  port(A: in std_logic;
  F: out std_logic);
end BUF;

architecture BUF_beh of BUF is
begin
  F <= A;
end architecture;

library ieee;
use ieee.std_logic_1164.all;

entity TRI_BUF is
  port(A: in std_logic;
  E: in std_logic;
  F: out std_logic);
end TRI_BUF;

architecture TRI_BUF_beh of TRI_BUF is
begin
  F <= A when (E = '1') else 'Z';
end architecture;

library ieee;
use ieee.std_logic_1164.all;

entity BUS_TRANSCIEVER is
  port (d0: in std_logic;
        d1: in std_logic;
        d2: in std_logic;
        d3: in std_logic;
        d4: in std_logic;
        d5: in std_logic;
        d6: in std_logic;
        d7: in std_logic;
        EN: in std_logic; -- ENABLE.
        q0: out std_logic;
        q1: out std_logic;
        q2: out std_logic;
        q3: out std_logic;
        q4: out std_logic;
        q5: out std_logic;
        q6: out std_logic;
        q7: out std_logic);
end BUS_TRANSCIEVER;

architecture BUS_TRANSCIEVER_beh of BUS_TRANSCIEVER is
begin
q0 <= d0 when (EN ='1') else 'Z';
q1 <= d1 when (EN ='1') else 'Z';
q2 <= d2 when (EN ='1') else 'Z';
q3 <= d3 when (EN ='1') else 'Z';
q4 <= d4 when (EN ='1') else 'Z';
q5 <= d5 when (EN ='1') else 'Z';
q6 <= d6 when (EN ='1') else 'Z';
q7 <= d7 when (EN ='1') else 'Z';

end architecture;

CPU/REG.vhdl
library ieee;
use ieee.std_logic_1164.all;

entity REG8 is
  port (d0: in std_logic;
        d1: in std_logic;
        d2: in std_logic;
        d3: in std_logic;
        d4: in std_logic;
        d5: in std_logic;
        d6: in std_logic;
        d7: in std_logic;
        clk: in std_logic; -- clock.
        q0: in std_logic;
        q1: in std_logic;
        q2: in std_logic;
        q3: in std_logic;
        q4: in std_logic;
        q5: in std_logic;
        q6: in std_logic;
        q7: in std_logic);
end entity;

architecture REG8_beh of REG8 is

begin
  process(clk)
  begin
    if rising_edge(clk) then
      q0<=d0;
      q1<=d1;
      q2<=d2;
      q3<=d3;
      q4<=d4;
      q5<=d5;
      q6<=d6;
      q7<=d7;
    end if;
    end process;
      end architecture;

CPU/COUNTER.vhdl
library ieee;
use ieee.std_logic_1164.all;

entity COUNTER is
  port(d0: in std_logic;
       d1: in std_logic;
       d2: in std_logic;
       d3: in std_logic;
       d4: in std_logic;
       d5: in std_logic;
       d6: in std_logic;
       d7: in std_logic;
       q0: out std_logic;
       q1: out std_logic;
       q2: out std_logic;
       q3: out std_logic;
       q4: out std_logic;
       q5: out std_logic;
       q6: out std_logic;
       q7: out std_logic;
       clk: in std_logic;
       C_EN: in std_logic;
       J_EN: in std_logic);
    end COUNTER;

architecture COUNTER_arch of COUNTER is
  component REG8
  port (d0: in std_logic;
        d1: in std_logic;
        d2: in std_logic;
        d3: in std_logic;
        d4: in std_logic;
        d5: in std_logic;
        d6: in std_logic;
        d7: in std_logic;
        clk: in std_logic; -- clock.
        q0: out std_logic;
        q1: out std_logic;
        q2: out std_logic;
        q3: out std_logic;
        q4: out std_logic;
        q5: out std_logic;
        q6: out std_logic;
        q7: out std_logic);
  end component;
  component dual_XOR is
    port(A: in std_logic;
    B: in std_logic;
    F: out std_logic);
  end component;
  component dual_AND is --might not be needed
    port (A: in std_logic;
    B: in std_logic;
    F: out std_logic);
  end component;
  component BUS_TRANSCIEVER is
    port (d0: in std_logic;
          d1: in std_logic;
          d2: in std_logic;
          d3: in std_logic;
          d4: in std_logic;
          d5: in std_logic;
          d6: in std_logic;
          d7: in std_logic;
          EN: in std_logic; -- ENABLE.
          q0: out std_logic;
          q1: out std_logic;
          q2: out std_logic;
          q3: out std_logic;
          q4: out std_logic;
          q5: out std_logic;
          q6: out std_logic;
          q7: out std_logic);
  end component;
  component BUF
  port(A: in std_logic;
  F: out std_logic);
  end component;
  component INV is
    port (A: in std_logic;
    F: out std_logic);
  end component;
  signal i0,i1,i2,i3,i4,i5,i6,i7,o0,o1,o2,o3,o4,o5,o6,o7,ox0,ox1,ox2,ox3,ox4,ox5,ox6,ox7,ih0,ih1,ih2,ih3,ih4,ih5: std_logic;
begin
  IN_BUFFER: BUS_TRANSCIEVER port map (d0,d1,d2,d3,d4,d5,d6,d7,J_EN,i0,i1,i2,i3,i4,i5,i6,i7);
  COUNT_BUFFER: BUS_TRANSCIEVER port map (ox0,ox1,ox2,ox3,ox4,ox5,ox6,ox7,C_EN,i0,i1,i2,i3,i4,i5,i6,i7);
  REG: REG8 port map (i0,i1,i2,i3,i4,i5,i6,i7,clk,o0,o1,o2,o3,o4,o5,o6,o7);
  B0: BUF port map (o0,q0);
  B1: BUF port map (o1,q1);
  B2: BUF port map (o2,q2);
  B3: BUF port map (o3,q3);
  B4: BUF port map (o4,q4);
  B5: BUF port map (o5,q5);
  B6: BUF port map (o6,q6);
  B7: BUF port map (o7,q7);
  L0: INV port map (o0,ox0);
  L1: dual_XOR port map (o0,o1,ox1);
  A1: dual_AND port map (o0,o1,ih0);
  L2: dual_XOR port map (ih0,o2,ox2);
  A2: dual_AND port map (ih0,o2,ih1);
  L3: dual_XOR port map (ih1,o3,ox3);
  A3: dual_AND port map (ih1,o3,ih2);
  L4: dual_XOR port map (ih2,o4,ox4);
  A4: dual_AND port map (ih2,o4,ih3);
  L5: dual_XOR port map (ih3,o5,ox5);
  A5: dual_AND port map (ih3,o5,ih4);
  L6: dual_XOR port map (ih4,o6,ox6);
  A6: dual_AND port map (ih4,o6,ih5);
  L7: dual_XOR port map (ih5,o7,ox7);

end architecture;

CPU/COUNTER_tb.vhdl
library ieee;
use ieee.std_logic_1164.all;

entity COUNTER_tb is
end entity;

architecture COUNTER_tb_test of COUNTER_tb is
component COUNTER
port(d0: in std_logic;
     d1: in std_logic;
     d2: in std_logic;
     d3: in std_logic;
     d4: in std_logic;
     d5: in std_logic;
     d6: in std_logic;
     d7: in std_logic;
     q0: out std_logic;
     q1: out std_logic;
     q2: out std_logic;
     q3: out std_logic;
     q4: out std_logic;
     q5: out std_logic;
     q6: out std_logic;
     q7: out std_logic;
     clk: in std_logic;
     C_EN: in std_logic;
     J_EN: in std_logic);

end component;
signal d0,d1,d2,d3,d4,d5,d6,d7,q0,q1,q2,q3,q4,q5,q6,q7,clk,C_EN,J_EN:std_logic;
begin
mapping: COUNTER port map (d0,d1,d2,d3,d4,d5,d6,d7,q0,q1,q2,q3,q4,q5,q6,q7,clk,C_EN,J_EN);
process begin
d0<='1';
d1<='1';
d2<='1';
d3<='1';
d4<='1';
d5<='1';
d6<='1';
d7<='1';
J_EN <='1';
C_EN <= '0';
clk <= '0';
wait for 1 ns;
clk <='1';
wait for 1 ns;
J_EN <='0';
C_EN <='1';
clk<='0';
wait for 1 ns;
clk <='1';
wait for 1 ns;
clk<='0';
wait for 1 ns;
clk<='1';
wait for 1 ns;
clk<='0';
wait for 1 ns;
clk<='1';
wait for 1 ns;
clk<='0';
wait for 1 ns;
clk<='1';
wait for 1 ns;
clk<='0';
wait for 1 ns;
clk<='1';
wait for 1 ns;
clk<='0';
C_EN <='0';
J_EN <='1';
d0<='0';
d1<='0';
d2<='0';
d3<='1';
d4<='0';
d5<='1';
d6<='0';
d7<='1';
wait for 1 ns;
clk<='1';
wait for 1 ns;
assert false report "Yeet done";
wait;
end process;
end architecture;

CPU/COUNTER.vcd
$date
  Fri Jan 17 19:58:01 2020
$end
$version
  GHDL v0
$end
$timescale
  1 fs
$end
$scope module standard $end
$upscope $end
$scope module std_logic_1164 $end
$upscope $end
$scope module counter_tb $end
$var reg 1 ! d0 $end
$var reg 1 " d1 $end
$var reg 1 # d2 $end
$var reg 1 $ d3 $end
$var reg 1 % d4 $end
$var reg 1 & d5 $end
$var reg 1 ' d6 $end
$var reg 1 ( d7 $end
$var reg 1 ) q0 $end
$var reg 1 * q1 $end
$var reg 1 + q2 $end
$var reg 1 , q3 $end
$var reg 1 - q4 $end
$var reg 1 . q5 $end
$var reg 1 / q6 $end
$var reg 1 0 q7 $end
$var reg 1 1 clk $end
$var reg 1 2 c_en $end
$var reg 1 3 j_en $end
$scope module mapping $end
$var reg 1 4 d0 $end
$var reg 1 5 d1 $end
$var reg 1 6 d2 $end
$var reg 1 7 d3 $end
$var reg 1 8 d4 $end
$var reg 1 9 d5 $end
$var reg 1 : d6 $end
$var reg 1 ; d7 $end
$var reg 1 < q0 $end
$var reg 1 = q1 $end
$var reg 1 > q2 $end
$var reg 1 ? q3 $end
$var reg 1 @ q4 $end
$var reg 1 A q5 $end
$var reg 1 B q6 $end
$var reg 1 C q7 $end
$var reg 1 D clk $end
$var reg 1 E c_en $end
$var reg 1 F j_en $end
$var reg 1 G i0 $end
$var reg 1 H i1 $end
$var reg 1 I i2 $end
$var reg 1 J i3 $end
$var reg 1 K i4 $end
$var reg 1 L i5 $end
$var reg 1 M i6 $end
$var reg 1 N i7 $end
$var reg 1 O o0 $end
$var reg 1 P o1 $end
$var reg 1 Q o2 $end
$var reg 1 R o3 $end
$var reg 1 S o4 $end
$var reg 1 T o5 $end
$var reg 1 U o6 $end
$var reg 1 V o7 $end
$var reg 1 W ox0 $end
$var reg 1 X ox1 $end
$var reg 1 Y ox2 $end
$var reg 1 Z ox3 $end
$var reg 1 [ ox4 $end
$var reg 1 \ ox5 $end
$var reg 1 ] ox6 $end
$var reg 1 ^ ox7 $end
$var reg 1 _ ih0 $end
$var reg 1 ` ih1 $end
$var reg 1 a ih2 $end
$var reg 1 b ih3 $end
$var reg 1 c ih4 $end
$var reg 1 d ih5 $end
$scope module in_buffer $end
$var reg 1 e d0 $end
$var reg 1 f d1 $end
$var reg 1 g d2 $end
$var reg 1 h d3 $end
$var reg 1 i d4 $end
$var reg 1 j d5 $end
$var reg 1 k d6 $end
$var reg 1 l d7 $end
$var reg 1 m en $end
$var reg 1 n q0 $end
$var reg 1 o q1 $end
$var reg 1 p q2 $end
$var reg 1 q q3 $end
$var reg 1 r q4 $end
$var reg 1 s q5 $end
$var reg 1 t q6 $end
$var reg 1 u q7 $end
$upscope $end
$scope module count_buffer $end
$var reg 1 v d0 $end
$var reg 1 w d1 $end
$var reg 1 x d2 $end
$var reg 1 y d3 $end
$var reg 1 z d4 $end
$var reg 1 { d5 $end
$var reg 1 | d6 $end
$var reg 1 } d7 $end
$var reg 1 !" en $end
$var reg 1 "" q0 $end
$var reg 1 #" q1 $end
$var reg 1 $" q2 $end
$var reg 1 %" q3 $end
$var reg 1 &" q4 $end
$var reg 1 '" q5 $end
$var reg 1 (" q6 $end
$var reg 1 )" q7 $end
$upscope $end
$scope module reg $end
$var reg 1 *" d0 $end
$var reg 1 +" d1 $end
$var reg 1 ," d2 $end
$var reg 1 -" d3 $end
$var reg 1 ." d4 $end
$var reg 1 /" d5 $end
$var reg 1 0" d6 $end
$var reg 1 1" d7 $end
$var reg 1 2" clk $end
$var reg 1 3" q0 $end
$var reg 1 4" q1 $end
$var reg 1 5" q2 $end
$var reg 1 6" q3 $end
$var reg 1 7" q4 $end
$var reg 1 8" q5 $end
$var reg 1 9" q6 $end
$var reg 1 :" q7 $end
$upscope $end
$scope module b0 $end
$var reg 1 ;" a $end
$var reg 1 <" f $end
$upscope $end
$scope module b1 $end
$var reg 1 =" a $end
$var reg 1 >" f $end
$upscope $end
$scope module b2 $end
$var reg 1 ?" a $end
$var reg 1 @" f $end
$upscope $end
$scope module b3 $end
$var reg 1 A" a $end
$var reg 1 B" f $end
$upscope $end
$scope module b4 $end
$var reg 1 C" a $end
$var reg 1 D" f $end
$upscope $end
$scope module b5 $end
$var reg 1 E" a $end
$var reg 1 F" f $end
$upscope $end
$scope module b6 $end
$var reg 1 G" a $end
$var reg 1 H" f $end
$upscope $end
$scope module b7 $end
$var reg 1 I" a $end
$var reg 1 J" f $end
$upscope $end
$scope module l0 $end
$var reg 1 K" a $end
$var reg 1 L" f $end
$upscope $end
$scope module l1 $end
$var reg 1 M" a $end
$var reg 1 N" b $end
$var reg 1 O" f $end
$upscope $end
$scope module a1 $end
$var reg 1 P" a $end
$var reg 1 Q" b $end
$var reg 1 R" f $end
$upscope $end
$scope module l2 $end
$var reg 1 S" a $end
$var reg 1 T" b $end
$var reg 1 U" f $end
$upscope $end
$scope module a2 $end
$var reg 1 V" a $end
$var reg 1 W" b $end
$var reg 1 X" f $end
$upscope $end
$scope module l3 $end
$var reg 1 Y" a $end
$var reg 1 Z" b $end
$var reg 1 [" f $end
$upscope $end
$scope module a3 $end
$var reg 1 \" a $end
$var reg 1 ]" b $end
$var reg 1 ^" f $end
$upscope $end
$scope module l4 $end
$var reg 1 _" a $end
$var reg 1 `" b $end
$var reg 1 a" f $end
$upscope $end
$scope module a4 $end
$var reg 1 b" a $end
$var reg 1 c" b $end
$var reg 1 d" f $end
$upscope $end
$scope module l5 $end
$var reg 1 e" a $end
$var reg 1 f" b $end
$var reg 1 g" f $end
$upscope $end
$scope module a5 $end
$var reg 1 h" a $end
$var reg 1 i" b $end
$var reg 1 j" f $end
$upscope $end
$scope module l6 $end
$var reg 1 k" a $end
$var reg 1 l" b $end
$var reg 1 m" f $end
$upscope $end
$scope module a6 $end
$var reg 1 n" a $end
$var reg 1 o" b $end
$var reg 1 p" f $end
$upscope $end
$scope module l7 $end
$var reg 1 q" a $end
$var reg 1 r" b $end
$var reg 1 s" f $end
$upscope $end
$upscope $end
$upscope $end
$enddefinitions $end
#0
1!
1"
1#
1$
1%
1&
1'
1(
U)
U*
U+
U,
U-
U.
U/
U0
01
02
13
14
15
16
17
18
19
1:
1;
U<
U=
U>
U?
U@
UA
UB
UC
0D
0E
1F
1G
1H
1I
1J
1K
1L
1M
1N
UO
UP
UQ
UR
US
UT
UU
UV
UW
UX
UY
UZ
U[
U\
U]
U^
U_
U`
Ua
Ub
Uc
Ud
1e
1f
1g
1h
1i
1j
1k
1l
1m
1n
1o
1p
1q
1r
1s
1t
1u
Uv
Uw
Ux
Uy
Uz
U{
U|
U}
0!"
1""
1#"
1$"
1%"
1&"
1'"
1("
1)"
1*"
1+"
1,"
1-"
1."
1/"
10"
11"
02"
U3"
U4"
U5"
U6"
U7"
U8"
U9"
U:"
U;"
U<"
U="
U>"
U?"
U@"
UA"
UB"
UC"
UD"
UE"
UF"
UG"
UH"
UI"
UJ"
UK"
UL"
UM"
UN"
UO"
UP"
UQ"
UR"
US"
UT"
UU"
UV"
UW"
UX"
UY"
UZ"
U["
U\"
U]"
U^"
U_"
U`"
Ua"
Ub"
Uc"
Ud"
Ue"
Uf"
Ug"
Uh"
Ui"
Uj"
Uk"
Ul"
Um"
Un"
Uo"
Up"
Uq"
Ur"
Us"
#1000000
1)
1*
1+
1,
1-
1.
1/
10
11
1<
1=
1>
1?
1@
1A
1B
1C
1D
1O
1P
1Q
1R
1S
1T
1U
1V
0W
0X
0Y
0Z
0[
0\
0]
0^
1_
1`
1a
1b
1c
1d
1n
1o
1p
1q
1r
1s
1t
1u
0v
0w
0x
0y
0z
0{
0|
0}
1""
1#"
1$"
1%"
1&"
1'"
1("
1)"
12"
13"
14"
15"
16"
17"
18"
19"
1:"
1;"
1<"
1="
1>"
1?"
1@"
1A"
1B"
1C"
1D"
1E"
1F"
1G"
1H"
1I"
1J"
1K"
0L"
1M"
1N"
0O"
1P"
1Q"
1R"
1S"
1T"
0U"
1V"
1W"
1X"
1Y"
1Z"
0["
1\"
1]"
1^"
1_"
1`"
0a"
1b"
1c"
1d"
1e"
1f"
0g"
1h"
1i"
1j"
1k"
1l"
0m"
1n"
1o"
1p"
1q"
1r"
0s"
#2000000
01
12
03
0D
1E
0F
0G
0H
0I
0J
0K
0L
0M
0N
0m
0n
0o
0p
0q
0r
0s
0t
0u
1!"
0""
0#"
0$"
0%"
0&"
0'"
0("
0)"
0*"
0+"
0,"
0-"
0."
0/"
00"
01"
02"
#3000000
0)
0*
0+
0,
0-
0.
0/
00
11
0<
0=
0>
0?
0@
0A
0B
0C
1D
1G
0I
0J
0K
0L
0M
0N
0O
0P
0Q
0R
0S
0T
0U
0V
1W
0Y
0Z
0[
0\
0]
0^
0_
0`
0a
0b
0c
0d
1n
0p
0q
0r
0s
0t
0u
1v
0x
0y
0z
0{
0|
0}
1""
0$"
0%"
0&"
0'"
0("
0)"
1*"
0,"
0-"
0."
0/"
00"
01"
12"
03"
04"
05"
06"
07"
08"
09"
0:"
0;"
0<"
0="
0>"
0?"
0@"
0A"
0B"
0C"
0D"
0E"
0F"
0G"
0H"
0I"
0J"
0K"
1L"
0M"
0N"
0P"
0Q"
0R"
0S"
0T"
0U"
0V"
0W"
0X"
0Y"
0Z"
0["
0\"
0]"
0^"
0_"
0`"
0a"
0b"
0c"
0d"
0e"
0f"
0g"
0h"
0i"
0j"
0k"
0l"
0m"
0n"
0o"
0p"
0q"
0r"
0s"
#4000000
01
0D
02"
#5000000
1)
11
1<
1D
0G
1H
1O
0W
1X
0n
1o
0v
1w
0""
1#"
0*"
1+"
12"
13"
1;"
1<"
1K"
0L"
1M"
1O"
1P"
#6000000
01
0D
02"
#7000000
0)
1*
11
0<
1=
1D
1G
0O
1P
1W
1n
1v
1""
1*"
12"
03"
14"
0;"
0<"
1="
1>"
0K"
1L"
0M"
1N"
0P"
1Q"
#8000000
01
0D
02"
#9000000
1)
11
1<
1D
0G
0H
1I
1O
0W
0X
1Y
1_
0n
0o
1p
0v
0w
1x
0""
0#"
1$"
0*"
0+"
1,"
12"
13"
1;"
1<"
1K"
0L"
1M"
0O"
1P"
1R"
1S"
1U"
1V"
#10000000
01
0D
02"
#11000000
0)
0*
1+
11
0<
0=
1>
1D
1G
1I
0J
0O
0P
1Q
1W
1Y
0Z
0_
0`
1n
1p
0q
1v
1x
0y
1""
1$"
0%"
1*"
1,"
0-"
12"
03"
04"
15"
0;"
0<"
0="
0>"
1?"
1@"
0K"
1L"
0M"
0N"
0P"
0Q"
0R"
0S"
1T"
1U"
0V"
1W"
0X"
0Y"
0["
0\"
#12000000
0!
0"
0#
0%
0'
01
02
13
04
05
06
08
0:
0D
0E
1F
0G
0I
1J
1L
1N
0e
0f
0g
0i
0k
1m
0n
0o
0p
1q
0r
1s
0t
1u
0!"
0""
0#"
0$"
1%"
0&"
1'"
0("
1)"
0*"
0,"
1-"
1/"
11"
02"
#13000000
0+
1,
1.
10
11
0>
1?
1A
1C
1D
0Q
1R
1T
1V
0Y
1Z
1\
1^
0p
1q
1s
1u
0x
1y
1{
1}
0$"
1%"
1'"
1)"
12"
05"
16"
18"
1:"
0?"
0@"
1A"
1B"
1E"
1F"
1I"
1J"
0T"
0U"
0W"
1Z"
1["
1]"
1f"
1g"
1i"
1r"
1s"
