CPU/DPRAM.vhdl
library ieee;
use ieee.std_logic_1164.all;

entity DPRAM is
	port
	(
		data_a	: in std_logic_vector(7 downto 0);
		data_b	: in std_logic_vector(7 downto 0);
		addr_a	: in natural range 0 to 511;
		addr_b	: in natural range 0 to 511;
		we_a	: in std_logic := '1';
		we_b	: in std_logic := '1';
		clk		: in std_logic;
		q_a		: out std_logic_vector(7 downto 0);
		q_b		: out std_logic_vector(7 downto 0)
	);

end DPRAM;

architecture rtl of DPRAM is

	-- Build a 2-D array type for the RAM
	subtype word_t is std_logic_vector(7 downto 0);
	type memory_t is array(511 downto 0) of word_t;

	-- Declare the RAM
	shared variable ram : memory_t;

begin

	-- Port A
	process(clk)
	begin
		if(rising_edge(clk)) then
			if(we_a = '1') then
				ram(addr_a) := data_a;
			end if;
			q_a <= ram(addr_a);
		end if;
	end process;

	-- Port B
	process(clk)
	begin
		if(rising_edge(clk)) then
			if(we_b = '1') then
				ram(addr_b) := data_b;
			end if;
			q_b <= ram(addr_b);
		end if;
	end process;
end rtl;

CPU/DPRAM_tb.vhdl
library ieee;
use ieee.std_logic_1164.all;

entity DPRAM_tb is
end entity;


architecture DPRAM_tb_test of DPRAM_tb is
component DPRAM
port  (
    data_a	: in std_logic_vector(7 downto 0);
    data_b	: in std_logic_vector(7 downto 0);
    addr_a	: in std_logic_vector (8 downto 0);
		addr_b	: in std_logic_vector (8 downto 0);
    we_a	: in std_logic := '1';
    we_b	: in std_logic := '1';
    clk		: in std_logic;
    q_a		: out std_logic_vector(7 downto 0);
    q_b		: out std_logic_vector(7 downto 0)
  );

end component;
signal data_a, data_b,q_a,q_b : std_logic_vector(7 downto 0);
signal addr_a,addr_b: std_logic_vector (8 downto 0);
signal we_a, we_b, clk: std_logic;
begin
mapping: DPRAM port map (data_a,data_b,addr_a,addr_b,we_a,we_b,clk,q_a,q_b);
process begin
  clk<='0';
  we_b <='1';
  addr_b<="100000000";
  data_b<="00000001";
  wait for 1 ns;
  clk<='1';

  wait for 1 ns;
  clk<='0';
  addr_b<="100000001";
  data_b<="00000110";
  wait for 1 ns;
  clk<='1';

  wait for 1 ns;
  clk<='0';
  addr_b<="000000000";
  data_b<="00010000";
  wait for 1 ns;
  clk<='1';

  wait for 1 ns;
  clk<='0';
  addr_b<="000000001";
  data_b<="10000000";
  wait for 1 ns;
  clk<='1';

  wait for 1 ns;
  clk<='0';
  addr_b<="000000010";
  data_b<="00010000";
  wait for 1 ns;
  clk<='1';

  wait for 1 ns;
  clk<='0';
  addr_b<="000000011";
  data_b<="10000001";
  wait for 1 ns;
  clk<='1';

  wait for 1 ns;
  clk<='0';
  addr_b<="000000100";
  data_b<="00010001";
  wait for 1 ns;
  clk<='1';

  wait for 1 ns;
  clk<='0';
  addr_b<="000000101";
  data_b<="10000110";
  wait for 1 ns;
  clk<='1';

  wait for 1 ns;
  clk<='0';
  addr_b<="000000110";
  data_b<="11001001";
  wait for 1 ns;
  clk<='1';

  wait for 1 ns;
  clk<='0';
  addr_b<="000000111";
  data_b<="10000011";
  wait for 1 ns;
  clk<='1';

  wait for 1 ns;
  clk<='0';
  addr_b<="000001000";
  data_b<="11001001";
  wait for 1 ns;
  clk<='1';

  wait for 1 ns;
  clk<='0';
  addr_b<="000001001";
  data_b<="10000000";
  wait for 1 ns;
  clk<='1';

  wait for 1 ns;
  clk<='0';
  addr_b<="000001010";
  data_b<="11001001";
  wait for 1 ns;
  clk<='1';

  wait for 1 ns;
  clk<='0';
  addr_b<="000001011";
  data_b<="10000011";
  wait for 1 ns;
  clk<='1';

  wait for 1 ns;
  clk<='0';
  addr_b<="000001100";
  data_b<="11001001";
  wait for 1 ns;
  clk<='1';

  wait for 1 ns;
  clk<='0';
  addr_b<="000001101";
  data_b<="10000001";
  wait for 1 ns;
  clk<='1';

  wait for 1 ns;
  clk<='0';
  addr_b<="000001110";
  data_b<="10000010";
  wait for 1 ns;
  clk <='1';
  wait for 1 ns;
  we_b<='0';
  clk<='1';
  wait for 1 ns;
  clk <= '1';
  wait for 1 ns;
  clk <='0';
  wait for 1 ns;
  addr_b<="000000001";
  clk<='1';
  wait for 1 ns;
  clk<='0';

  wait for 1 ns;
  addr_b<="000000010";
  clk<='1';
  wait for 1 ns;
  clk<='0';

  wait for 1 ns;
  addr_b<="000000011";
  clk<='1';
  wait for 1 ns;
  clk<='0';

  wait for 1 ns;
  addr_b<="000000100";
  clk<='1';
  wait for 1 ns;
  clk<='0';

  wait for 1 ns;
  addr_b<="000000101";
  clk<='1';
  wait for 1 ns;
  clk<='0';

  wait for 1 ns;
  clk<='1';
  wait for 1 ns;
  clk<='0';

  wait for 1 ns;
  clk<='1';
  wait for 1 ns;
  clk<='0';

  wait for 1 ns;
  clk<='1';
  wait for 1 ns;
  clk<='0';

  wait for 1 ns;
  clk<='1';
  wait for 1 ns;
  clk<='0';

  wait for 1 ns;
  clk<='1';
  wait for 1 ns;
  clk<='0';

  wait for 1 ns;
  clk<='1';
  wait for 1 ns;
  clk<='0';

  wait for 1 ns;
  clk<='1';
  wait for 1 ns;
  clk<='0';

  wait for 1 ns;
  clk<='1';
  wait for 1 ns;
  clk<='0';

  wait for 1 ns;
  clk<='1';
  wait for 1 ns;
  clk<='0';

  wait for 1 ns;
  clk<='1';
  wait for 1 ns;
  clk<='0';

  wait for 1 ns;
  clk<='1';
  wait for 1 ns;
  clk<='0';

  wait for 1 ns;
  clk<='1';
  wait for 1 ns;
  clk<='0';

  wait for 1 ns;
  clk<='1';
  wait for 1 ns;
  clk<='0';

  wait for 1 ns;
  clk<='1';
  wait for 1 ns;
  clk<='0';

  wait for 1 ns;
  clk<='1';
  wait for 1 ns;
  clk<='0';

  wait for 1 ns;
  clk<='1';
  wait for 1 ns;
  clk<='0';

  wait for 1 ns;
  clk<='1';
  wait for 1 ns;
  clk<='0';

  wait for 1 ns;
  clk<='1';
  wait for 1 ns;
  clk<='0';

  wait for 1 ns;
  clk<='1';
  wait for 1 ns;
  clk<='0';

  wait for 1 ns;
  clk<='1';
  wait for 1 ns;
  clk<='0';

  wait for 1 ns;
  clk<='1';
  wait for 1 ns;
  clk<='0';

  wait for 1 ns;
  clk<='1';
  wait for 1 ns;
  clk<='0';

  wait for 1 ns;
  clk<='1';
  wait for 1 ns;
  clk<='0';

  wait for 1 ns;
  clk<='1';
  wait for 1 ns;
  clk<='0';
  assert false report "Yeet done";
  wait;
end process;
end architecture;

CPU/DPRAM.vcd
$date
  Wed Jan 22 14:57:58 2020
$end
$version
  GHDL v0
$end
$timescale
  1 fs
$end
$scope module standard $end
$upscope $end
$scope module std_logic_1164 $end
$upscope $end
$scope module numeric_std $end
$upscope $end
$scope module dpram_tb $end
$var reg 8 ! data_a[7:0] $end
$var reg 8 " data_b[7:0] $end
$var reg 8 # q_a[7:0] $end
$var reg 8 $ q_b[7:0] $end
$var reg 9 % addr_a[8:0] $end
$var reg 9 & addr_b[8:0] $end
$var reg 1 ' we_a $end
$var reg 1 ( we_b $end
$var reg 1 ) clk $end
$scope module mapping $end
$var reg 8 * data_a[7:0] $end
$var reg 8 + data_b[7:0] $end
$var reg 9 , addr_a[8:0] $end
$var reg 9 - addr_b[8:0] $end
$var reg 1 . we_a $end
$var reg 1 / we_b $end
$var reg 1 0 clk $end
$var reg 8 1 q_a[7:0] $end
$var reg 8 2 q_b[7:0] $end
$upscope $end
$upscope $end
$enddefinitions $end
#0
bUUUUUUUU !
b00000001 "
bUUUUUUUU #
bUUUUUUUU $
bUUUUUUUUU %
b100000000 &
U'
1(
0)
bUUUUUUUU *
b00000001 +
bUUUUUUUUU ,
b100000000 -
U.
1/
00
bUUUUUUUU 1
bUUUUUUUU 2
#1000000
b00000001 $
1)
10
b00000001 2
#2000000
b00000110 "
b100000001 &
0)
b00000110 +
b100000001 -
00
#3000000
b00000110 $
1)
10
b00000110 2
#4000000
b00010000 "
b000000000 &
0)
b00010000 +
b000000000 -
00
#5000000
b00010000 #
b00010000 $
1)
10
b00010000 1
b00010000 2
#6000000
b10000000 "
b000000001 &
0)
b10000000 +
b000000001 -
00
#7000000
b10000000 $
1)
10
b10000000 2
#8000000
b00010000 "
b000000010 &
0)
b00010000 +
b000000010 -
00
#9000000
b00010000 $
1)
10
b00010000 2
#10000000
b10000001 "
b000000011 &
0)
b10000001 +
b000000011 -
00
#11000000
b10000001 $
1)
10
b10000001 2
#12000000
b00010001 "
b000000100 &
0)
b00010001 +
b000000100 -
00
#13000000
b00010001 $
1)
10
b00010001 2
#14000000
b10000110 "
b000000101 &
0)
b10000110 +
b000000101 -
00
#15000000
b10000110 $
1)
10
b10000110 2
#16000000
b11001001 "
b000000110 &
0)
b11001001 +
b000000110 -
00
#17000000
b11001001 $
1)
10
b11001001 2
#18000000
b10000011 "
b000000111 &
0)
b10000011 +
b000000111 -
00
#19000000
b10000011 $
1)
10
b10000011 2
#20000000
b11001001 "
b000001000 &
0)
b11001001 +
b000001000 -
00
#21000000
b11001001 $
1)
10
b11001001 2
#22000000
b10000000 "
b000001001 &
0)
b10000000 +
b000001001 -
00
#23000000
b10000000 $
1)
10
b10000000 2
#24000000
b11001001 "
b000001010 &
0)
b11001001 +
b000001010 -
00
#25000000
b11001001 $
1)
10
b11001001 2
#26000000
b10000011 "
b000001011 &
0)
b10000011 +
b000001011 -
00
#27000000
b10000011 $
1)
10
b10000011 2
#28000000
b11001001 "
b000001100 &
0)
b11001001 +
b000001100 -
00
#29000000
b11001001 $
1)
10
b11001001 2
#30000000
b10000001 "
b000001101 &
0)
b10000001 +
b000001101 -
00
#31000000
b10000001 $
1)
10
b10000001 2
#32000000
b10000010 "
b000001110 &
0)
b10000010 +
b000001110 -
00
#33000000
b10000010 $
1)
10
b10000010 2
#34000000
0(
0/
#35000000
#36000000
0)
00
#37000000
b10000000 $
b000000001 &
1)
b000000001 -
10
b10000000 2
#38000000
0)
00
#39000000
b00010000 $
b000000010 &
1)
b000000010 -
10
b00010000 2
#40000000
0)
00
#41000000
b10000001 $
b000000011 &
1)
b000000011 -
10
b10000001 2
#42000000
0)
00
#43000000
b00010001 $
b000000100 &
1)
b000000100 -
10
b00010001 2
#44000000
0)
00
#45000000
b10000110 $
b000000101 &
1)
b000000101 -
10
b10000110 2
